{
  "articles": [
    {
      "title": null,
      "media_name": "Australian Broadcast Company (ABC)",
      "author": null,
      "url": "https://www.abc.net.au/qanda/2020-10-02/11933296",
      "metrics": {
        "age": 21692280
      }
    },
    {
      "title": null,
      "media_name": "Daily Telegraph Australia",
      "author": null,
      "url": "https://www.dailytelegraph.com.au/coronavirus/bombshell-dossier-lays-out-case-against-chinese-bat-virus-program/news-story/55add857058731c9c71c0e96ad17da60?nk=96d5fa1ab0b92bc193e900251f004b7c-1591282020",
      "metrics": {
        "age": 5794680
      }
    },
    {
      "title": null,
      "media_name": "Australian Broadcast Company (ABC)",
      "author": null,
      "url": "https://www.abc.net.au/qanda/2020-11-05/12211454",
      "metrics": {
        "age": 13829880
      }
    },
    {
      "title": null,
      "media_name": "The Age",
      "author": null,
      "url": "p5611i",
      "metrics": {
        "age": 24370645
      }
    },
    {
      "title": null,
      "media_name": "The Age",
      "author": null,
      "url": "p560aa",
      "metrics": {
        "age": 24370461
      }
    },
    {
      "title": null,
      "media_name": "Sydney Morning Herald",
      "author": null,
      "url": "p5611i",
      "metrics": {
        "age": 24370645
      }
    },
    {
      "title": null,
      "media_name": "The Age",
      "author": null,
      "url": "p5610i",
      "metrics": {
        "age": 24370264
      }
    },
    {
      "title": null,
      "media_name": "Sydney Morning Herald",
      "author": null,
      "url": "p560aa",
      "metrics": {
        "age": 24370461
      }
    },
    {
      "title": null,
      "media_name": "Sydney Morning Herald",
      "author": null,
      "url": "p5610i",
      "metrics": {
        "age": 24370264
      }
    },
    {
      "title": null,
      "media_name": "News.com.au",
      "author": null,
      "url": "http://www.news.com.au/finance/real-estate/melbourne-vic/pakenham-upper-pad-named-the-farm-a-bush-oasis-near-the-city/news-story/af7301ef41351181e4e1ed63c6bbbe93",
      "metrics": {
        "age": 24370140
      }
    }
  ]
}